README.txt
buildout.cfg
setup.py
versions.cfg
bootstrap/bootstrap.py
docs/HISTORY.txt
docs/INSTALL.txt
docs/LICENSE.ZPL
docs/LICENSE.txt
docs/SPONSORS.txt
src/psj/__init__.py
src/psj.content.egg-info/PKG-INFO
src/psj.content.egg-info/SOURCES.txt
src/psj.content.egg-info/dependency_links.txt
src/psj.content.egg-info/entry_points.txt
src/psj.content.egg-info/namespace_packages.txt
src/psj.content.egg-info/not-zip-safe
src/psj.content.egg-info/requires.txt
src/psj.content.egg-info/top_level.txt
src/psj/content/README.txt
src/psj/content/__init__.py
src/psj/content/config.py
src/psj/content/configure.zcml
src/psj/content/document.txt
src/psj/content/events.py
src/psj/content/interfaces.py
src/psj/content/setuphandlers.py
src/psj/content/tool.gif
src/psj/content/util.py
src/psj/content/util.txt
src/psj/content/browser/__init__.py
src/psj/content/browser/addMetadataSchema.zpt
src/psj/content/browser/configure.zcml
src/psj/content/browser/editMetadataSchema.zpt
src/psj/content/browser/listMetadataSchemas.zpt
src/psj/content/browser/metadata_edit.pt
src/psj/content/browser/metadatabox.pt
src/psj/content/browser/psjbook.pt
src/psj/content/browser/psjbook.py
src/psj/content/browser/psjcontent.css
src/psj/content/browser/psjdocument.pt
src/psj/content/browser/psjdocument.py
src/psj/content/browser/psjdocument_icon.gif
src/psj/content/browser/psjfile.pt
src/psj/content/browser/psjfolder.pt
src/psj/content/browser/psjissue.py
src/psj/content/browser/psjissue_icon.gif
src/psj/content/browser/psjmagazine.py
src/psj/content/browser/psjmagazine_icon.gif
src/psj/content/browser/psjretromagazine.py
src/psj/content/browser/psjvolume.py
src/psj/content/browser/psjvolume_icon.gif
src/psj/content/browser/viewlets.py
src/psj/content/content/__init__.py
src/psj/content/content/book.py
src/psj/content/content/configure.zcml
src/psj/content/content/file.py
src/psj/content/content/issue.py
src/psj/content/content/magazine.py
src/psj/content/content/postprint.py
src/psj/content/content/psjdocument.py
src/psj/content/content/retroarticle.py
src/psj/content/content/retromagazine.py
src/psj/content/content/review.py
src/psj/content/content/volume.py
src/psj/content/locales/psj.content.pot
src/psj/content/locales/de/LC_MESSAGES/psj.content.mo
src/psj/content/locales/de/LC_MESSAGES/psj.content.po
